<?xml version="1.0" encoding="UTF-8"?>
<?mso-application progid="Excel.Sheet"?>
<Workbook xmlns="urn:schemas-microsoft-com:office:spreadsheet"
xmlns:o="urn:schemas-microsoft-com:office:office"
xmlns:x="urn:schemas-microsoft-com:office:excel"
xmlns:ss="urn:schemas-microsoft-com:office:spreadsheet"
xmlns:html="http://www.w3.org/TR/REC-html40">
<Worksheet ss:Name="Table1">
	<Table>
		<Column ss:Index="2" ss:AutoFitWidth="0" ss:Width="110"/>
		<Column ss:Index="3" ss:AutoFitWidth="0" ss:Width="110"/>
		<Row>
			<Cell><Data ss:Type="String">ID</Data></Cell>
			<Cell><Data ss:Type="String">NAME</Data></Cell>
			<Cell><Data ss:Type="String">SEVERITY</Data></Cell>
		</Row>

		<Row>
			<Cell><Data ss:Type="Number">0</Data></Cell>
			<Cell><Data ss:Type="String">cow's milk</Data></Cell>
			<Cell><Data ss:Type="String">low</Data></Cell>
		</Row>
		<Row>
			<Cell><Data ss:Type="Number">1</Data></Cell>
			<Cell><Data ss:Type="String">eggs</Data></Cell>
			<Cell><Data ss:Type="String">low</Data></Cell>
		</Row>
		<Row>
			<Cell><Data ss:Type="Number">2</Data></Cell>
			<Cell><Data ss:Type="String">peanuts</Data></Cell>
			<Cell><Data ss:Type="String">high</Data></Cell>
		</Row>
		<Row>
			<Cell><Data ss:Type="Number">3</Data></Cell>
			<Cell><Data ss:Type="String">fish</Data></Cell>
			<Cell><Data ss:Type="String">low</Data></Cell>
		</Row>
		<Row>
			<Cell><Data ss:Type="Number">4</Data></Cell>
			<Cell><Data ss:Type="String">shellfish</Data></Cell>
			<Cell><Data ss:Type="String">high</Data></Cell>
		</Row>
		<Row>
			<Cell><Data ss:Type="Number">5</Data></Cell>
			<Cell><Data ss:Type="String">tree nuts</Data></Cell>
			<Cell><Data ss:Type="String">high</Data></Cell>
		</Row>
		<Row>
			<Cell><Data ss:Type="Number">6</Data></Cell>
			<Cell><Data ss:Type="String">wheat</Data></Cell>
			<Cell><Data ss:Type="String">medium</Data></Cell>
		</Row>
		<Row>
			<Cell><Data ss:Type="Number">7</Data></Cell>
			<Cell><Data ss:Type="String">soy</Data></Cell>
			<Cell><Data ss:Type="String">medium</Data></Cell>
		</Row>	</Table>
</Worksheet>
</Workbook>
